pets/__init__.py
pets/cli_manager.py
pets/cohort.py
pets/cohort_analyser_methods.py
pets/cons.py
pets/genomic_features.py
pets/genomic_prioritizer.py
pets/io.py
pets/main_modules.py
pets/pets.py
pets/report_pets.py
pets/external_data/chromosome_sizes_hg18.txt
pets/external_data/chromosome_sizes_hg19.txt
pets/external_data/chromosome_sizes_hg38.txt
pets/external_data/disorder_classes
pets/external_data/gencode.v43.basic.annotation.gtf.gz
pets/external_data/hgnc_complete_set.txt
pets/external_data/hp.json
pets/external_data/mondo.obo
pets/external_data/transform.py
pets/external_data/uniq_hpo_with_CI.txt
pets/parsers/__init__.py
pets/parsers/cohort_parser.py
pets/parsers/coord_parser.py
pets/parsers/file_parser.py
pets/parsers/reference_parser.py
pets/templates/cluster_report.txt
pets/templates/cohort_report.txt
pets/templates/evidence_profile.txt
pets/templates/individual_prioreport.txt
pets/templates/integrated_by_patient_prioreport.txt
pets/templates/integrated_by_prioritizer_prioreport.txt
pets/templates/patient_report.txt
pets/templates/prioritizer_vs_prioritizer.txt
pets/templates/reg2phen_report.txt
py_pets-1.3.1.dist-info/licenses/LICENSE.txt
py_pets-1.3.1.dist-info/METADATA
py_pets-1.3.1.dist-info/WHEEL
py_pets-1.3.1.dist-info/entry_points.txt
py_pets-1.3.1.dist-info/top_level.txt
py_pets-1.3.1.dist-info/RECORD
