Metadata-Version: 2.4
Name: py_pets
Version: 1.3.1
Summary: Patient Exploration Tools Suite (PETS)
Home-page: https://github.com/seoanezonjic/pets
Author: seoanezonjic
Author-email: seoanezonjic@uma.es
License: MIT
Project-URL: Documentation, https://github.com/seoanezonjic/pets
Platform: any
Classifier: Development Status :: 4 - Beta
Classifier: Programming Language :: Python
License-File: LICENSE.txt
Requires-Dist: importlib-metadata; python_version < "3.8"
Requires-Dist: numpy
Requires-Dist: scipy
Requires-Dist: pandas
Requires-Dist: xgboost
Requires-Dist: requests
Requires-Dist: py_exp_calc
Requires-Dist: py_semtools
Requires-Dist: py_report_html
Requires-Dist: NetAnalyzer
Requires-Dist: varcode
Requires-Dist: gpsea
Provides-Extra: testing
Requires-Dist: setuptools; extra == "testing"
Requires-Dist: pytest; extra == "testing"
Requires-Dist: pytest-cov; extra == "testing"
Dynamic: license-file
